rejectax/__init__.py
rejectax/rejectax.py
rejectax-0.0.2.dist-info/LICENSE
rejectax-0.0.2.dist-info/METADATA
rejectax-0.0.2.dist-info/WHEEL
rejectax-0.0.2.dist-info/top_level.txt
rejectax-0.0.2.dist-info/RECORD
