Metadata-Version: 2.1
Name: rejectax
Version: 0.0.2
Summary: rejectax
Home-page: https://github.com/mdmould/rejectax
Author: Matthew Mould
Author-email: mattdmould@gmail.com
License: MIT
Requires-Python: >=3.10
License-File: LICENSE
Requires-Dist: jax
Requires-Dist: equinox
Requires-Dist: tqdm
